Workbook
Name aporte: Plan1!$C$18
Name apote: Plan1!$C$18
Name rendimento_carteira: Plan1!$C$13
Name taxa_mensal: Plan1!$C$20

Sheet Plan1
B11: CONFIGURAÇÕES
B12: Salário | C12: 5000
B13: Rendimento da carteira | C13: 0.01
B14: Sugestão de investimento | C14: =C12*30% -> 1500
B17: INVESTIMENTO MENSAL
B18: Quanto investir por mês; | C18: 750
A19: 2 | B19: Por quantos anos; | C19: 5
A20: 5 | B20: Qual a taxa de rendimento mensal; | C20: 0.01079
A21: 10 | B21: Quanto de patrimônio vai acumular; | C21: =FV(C20,C19*12,C18*-1) -> 62832.685
A22: 20 | B22: Quanto vai receber de dividendos por mês. | C22: =C21*1% -> 628.32685
A23: 30
B24: CENÁRIOS | D24: DIVIDENDO
B25: Quanto em 2 anos? | C25: =FV($C$20,$A19*12,$C$18*-1) -> 20420.72 | D25: =C25*rendimento_carteira -> 204.2072
B26: Quanto em 5 anos? | C26: =FV($C$20,$A20*12,$C$18*-1) -> 62832.685 | D26: =C26*rendimento_carteira -> 628.32685
B27: Quanto em 10 anos? | C27: =FV($C$20,$A21*12,$C$18*-1) -> 182463.16 | D27: =C27*rendimento_carteira -> 1824.6316
B28: Quanto em 20 anos? | C28: =FV($C$20,$A22*12,$C$18*-1) -> 843898.8 | D28: =C28*rendimento_carteira -> 8438.988
B29: Quanto em 30 anos? | C29: =FV($C$20,$A23*12,$C$18*-1) -> 3241627.2 | D29: =C29*rendimento_carteira -> 32416.272
B31: Perfil | C31: Conservador
B32: Valor a ser investido por mês | C32: =C18 -> 750
B34: Tipo de FII | C34: Percentual sugerido | D34: Valores
B35: Papel | C35: =VLOOKUP($C$31&"-"&B35,Plan2!$B$6:$E$23,4,FALSE) -> 0.3 | D35: =C35*$C$32 -> 225
B36: Tijolo | C36: =VLOOKUP($C$31&"-"&B36,Plan2!$B$6:$E$23,4,FALSE) -> 0.5 | D36: =C36*$C$32 -> 375
B37: Híbridos | C37: =VLOOKUP($C$31&"-"&B37,Plan2!$B$6:$E$23,4,FALSE) -> 0.1 | D37: =C37*$C$32 -> 75
B38: FOFs | C38: =VLOOKUP($C$31&"-"&B38,Plan2!$B$6:$E$23,4,FALSE) -> 0.1 | D38: =C38*$C$32 -> 75
B39: Desenvolvimento | C39: =VLOOKUP($C$31&"-"&B39,Plan2!$B$6:$E$23,4,FALSE) -> 0 | D39: =C39*$C$32 -> 0
B40: Hotelarias | C40: =VLOOKUP($C$31&"-"&B40,Plan2!$B$6:$E$23,4,FALSE) -> 0 | D40: =C40*$C$32 -> 0

Sheet Plan2
B5: chave | C5: Conservador | D5: Tipo de FII
B6: =C6&"-"&D6 -> Conservador-Papel | C6: Conservador | D6: Papel | E6: 0.3
B7: =C7&"-"&D7 -> Conservador-Tijolo | C7: Conservador | D7: Tijolo | E7: 0.5
B8: =C8&"-"&D8 -> Conservador-Híbridos | C8: Conservador | D8: Híbridos | E8: 0.1
B9: =C9&"-"&D9 -> Conservador-FOFs | C9: Conservador | D9: FOFs | E9: 0.1
B10: =C10&"-"&D10 -> Conservador-Desenvolvimento | C10: Conservador | D10: Desenvolvimento | E10: 0
B11: =C11&"-"&D11 -> Conservador-Hotelarias | C11: Conservador | D11: Hotelarias | E11: 0
B12: =C12&"-"&D12 -> Moderado-Papel | C12: Moderado | D12: Papel | E12: 0.32
B13: =C13&"-"&D13 -> Moderado-Tijolo | C13: Moderado | D13: Tijolo | E13: 0.4
B14: =C14&"-"&D14 -> Moderado-Híbridos | C14: Moderado | D14: Híbridos | E14: 0.08
B15: =C15&"-"&D15 -> Moderado-FOFs | C15: Moderado | D15: FOFs | E15: 0.1
B16: =C16&"-"&D16 -> Moderado-Desenvolvimento | C16: Moderado | D16: Desenvolvimento | E16: 0.1
B17: =C17&"-"&D17 -> Moderado-Hotelarias | C17: Moderado | D17: Hotelarias | E17: 0.05
... B23: =C23&"-"&D23 -> Agressivo-Hotelarias | C23: Agressivo | D23: Hotelarias | E23: 0.1
